CHANGES.rst
MANIFEST.in
README.rst
setup.py
src/collective/__init__.py
src/collective.gelf.egg-info/PKG-INFO
src/collective.gelf.egg-info/SOURCES.txt
src/collective.gelf.egg-info/dependency_links.txt
src/collective.gelf.egg-info/entry_points.txt
src/collective.gelf.egg-info/namespace_packages.txt
src/collective.gelf.egg-info/not-zip-safe
src/collective.gelf.egg-info/requires.txt
src/collective.gelf.egg-info/top_level.txt
src/collective/gelf/__init__.py
src/collective/gelf/component.xml
src/collective/gelf/configure.zcml
src/collective/gelf/handlers.py