Metadata-Version: 1.1
Name: collective.gelf
Version: 0.9.2
Summary: Graylog logging handler for Plone
Home-page: https://github.com/datakurre/collective.gelf
Author: Asko Soukka
Author-email: asko.soukka@iki.fi
License: EUPL
Platform: UNKNOWN
Classifier: Programming Language :: Python
